{"stats":{"total":4,"passed":4},"status":"passed","newTests":[{"id":"0e11c8d01519718e09a33f6545ae76f9","name":"Login with valid user data","status":"passed","duration":870},{"id":"82a7389195acf6a71f63eb5ea11b1de7","name":"User successfully checkout two products","status":"passed","duration":2081},{"id":"3ad073c9d4ee1c10bea6a8b29ba1cfc4","name":"User successfully checkout one product","status":"passed","duration":3550},{"id":"d11f766b9c1e17cc221799abfdc67812","name":"Login with invalid user data","status":"passed","duration":459}],"flakyTests":[],"retryTests":[],"name":"Allure Report","duration":6960,"createdAt":1781073578860,"plugin":"Awesome","meta":{"reportId":"af87391e-1735-4cd3-8acb-e28c037140ca","singleFile":false,"withTestResultsLinks":true},"pluginId":"awesome","pullRequestHref":"","jobHref":"https://github.com/ardikun1412/wdio-web-cucumber-init/actions/runs/27258167917"}